zenodo_api_client-0.0.2.dist-info/licenses/LICENSE
zenodo_client/__init__.py
zenodo_client/model.py
zenodo_api_client-0.0.2.dist-info/METADATA
zenodo_api_client-0.0.2.dist-info/WHEEL
zenodo_api_client-0.0.2.dist-info/top_level.txt
zenodo_api_client-0.0.2.dist-info/RECORD
