Metadata-Version: 2.4
Name: zenodo-api-client
Version: 0.0.2
License-File: LICENSE
Requires-Dist: requests
Dynamic: license-file
Dynamic: requires-dist
